{
  "avtaler": [
    {
      "produktbetegnelse": "Innskuddpensjon",
      "kategori": "INNSKUDD",
      "startAlder": 67,
      "startMaaned": 1,
      "utbetalingsperiode": {
        "startAlder": 71,
        "startMaaned": 7,
        "sluttAlder": 75,
        "sluttMaaned": 1,
        "aarligUtbetaling": 100000,
        "grad": 100
      }
    },
    {
      "produktbetegnelse": "Innskuddpensjon",
      "kategori": "INNSKUDD_KOLL",
      "startAlder": 67,
      "startMaaned": 1,
      "utbetalingsperiode": {
        "startAlder": 67,
        "startMaaned": 1,
        "sluttAlder": 77,
        "sluttMaaned": 1,
        "aarligUtbetaling": 50000,
        "grad": 100
      }
    },
    {
      "produktbetegnelse": "Nordea Liv",
      "kategori": "PRIVAT_TP",
      "startAlder": 75,
      "startMaaned": 1,
      "utbetalingsperiode": {
        "startAlder": 75,
        "startMaaned": 1,
        "sluttAlder": 85,
        "sluttMaaned": 1,
        "aarligUtbetaling": 39582,
        "grad": 100
      }
    },
    {
      "produktbetegnelse": "Storebrand",
      "kategori": "PRIVAT_TP",
      "startAlder": 67,
      "startMaaned": 1,
      "utbetalingsperiode": {
        "startAlder": 67,
        "startMaaned": 1,
        "sluttAlder": 77,
        "sluttMaaned": 1,
        "aarligUtbetaling": 31298,
        "grad": 100
      }
    },
    {
      "produktbetegnelse": "Oslo Pensjonsforsikring",
      "kategori": "OFFENTLIG_TP",
      "startAlder": 67,
      "startMaaned": 1,
      "utbetalingsperiode": {
        "startAlder": 67,
        "startMaaned": 1,
        "aarligUtbetaling": 103264,
        "grad": 100
      }
    },
    {
      "produktbetegnelse": "DNB",
      "kategori": "FRIPOLISE",
      "startAlder": 67,
      "startMaaned": 1,
      "utbetalingsperiode": {
        "startAlder": 67,
        "startMaaned": 1,
        "sluttAlder": 77,
        "sluttMaaned": 8,
        "aarligUtbetaling": 37264,
        "grad": 100
      }
    },
    {
      "produktbetegnelse": "IPS",
      "kategori": "EGEN_SPARING",
      "startAlder": 70,
      "startMaaned": 6,
      "utbetalingsperiode": {
        "startAlder": 70,
        "startMaaned": 6,
        "sluttAlder": 75,
        "sluttMaaned": 6,
        "aarligUtbetaling": 41802,
        "grad": 100
      }
    }
  ],
  "utilgjengeligeSelskap": []
}
